{
  "muscle_hierarchy": {
    "Upper Body": {
      "level": "high",
      "muscles": {
        "Chest": {
          "level": "mid",
          "muscles": {
            "Upper Chest": { "level": "low" },
            "Mid Chest": { "level": "low" },
            "Lower Chest": { "level": "low" }
          }
        },
        "Back": {
          "level": "mid",
          "muscles": {
            "Lats": { "level": "low" },
            "Traps": { "level": "low" },
            "Mid Back": { "level": "low" },
            "Lower Back": { "level": "low" }
          }
        },
        "Shoulders": {
          "level": "mid",
          "muscles": {
            "Front Delts": { "level": "low" },
            "Side Delts": { "level": "low" },
            "Rear Delts": { "level": "low" }
          }
        },
        "Arms": {
          "level": "mid",
          "muscles": {
            "Biceps": { "level": "low" },
            "Triceps": { "level": "low" },
            "Forearms": { "level": "low" }
          }
        }
      }
    },
    "Lower Body": {
      "level": "high",
      "muscles": {
        "Quads": { "level": "mid" },
        "Hamstrings": { "level": "mid" },
        "Glutes": { "level": "mid" },
        "Hips": {
          "level": "mid",
          "muscles": {
            "Adductors": { "level": "low" },
            "Abductors": { "level": "low" },
            "Hip Flexors": { "level": "low" }
          }
        },
        "Calves": { "level": "mid" }
      }
    },
    "Core": {
      "level": "high",
      "muscles": {
        "Abs": { "level": "mid" },
        "Obliques": { "level": "mid" }
      }
    }
  },

  "muscle_aliases": {
    "Chest": ["Upper Chest", "Mid Chest", "Lower Chest"],
    "Back": ["Lats", "Traps", "Mid Back", "Lower Back"],
    "Shoulders": ["Front Delts", "Side Delts", "Rear Delts"],
    "Arms": ["Biceps", "Triceps", "Forearms"],

    "Quads": ["Quads"],
    "Hamstrings": ["Hamstrings"],
    "Glutes": ["Glutes"],
    "Calves": ["Calves"],
    "Hips": ["Adductors", "Abductors", "Hip Flexors"],

    "Abs": ["Abs"],
    "Obliques": ["Obliques"],

    "Upper Body": ["Chest", "Back", "Shoulders", "Arms"],
    "Lower Body": ["Quads", "Hamstrings", "Glutes", "Hips", "Calves"],
    "Core": ["Abs", "Obliques"]
  }
}